<item>
<itemlevel>200</itemlevel>
<displayid>52400</displayid>
<displayslot>10</displayslot>
<iconpath>inv_gauntlets_16</iconpath>
<stats>
<armor>181</armor>
<stamina>42</stamina>
<intellect>44</intellect>
<spirit>53</spirit>
<spellpower>59</spellpower>
</stats>
<quality>Rare</quality>
<type>Cloth</type>
<faction>Neutral</faction>
<bind>BoP</bind>
<socketcolor1>Yellow</socketcolor1>
<socketbonus>
<stamina>6</stamina>
</socketbonus>
<name>Gloves of Distorted Time</name>
<id>37687</id>
<slot>Hands</slot>
</item>