<item>
<itemlevel>213</itemlevel>
<displayid>0</displayid>
<displayslot>0</displayslot>
<iconpath>inv_shoulder_29</iconpath>
<stats>
<armor>1723</armor>
<stamina>55</stamina>
<intellect>57</intellect>
<spellpower>78</spellpower>
<critrating>55</critrating>
<hasterating>35</hasterating>
</stats>
<quality>Epic</quality>
<setname>Redemption Regalia</setname>
<type>Plate</type>
<faction>Neutral</faction>
<requiredclasses>Paladin</requiredclasses>
<bind>BoP</bind>
<socketcolor1>Yellow</socketcolor1>
<socketbonus>
<mp5>2</mp5>
</socketbonus>
<name>Valorous Redemption Spaulders</name>
<id>40573</id>
<slot>Shoulders</slot>
</item>