<item>
<itemlevel>200</itemlevel>
<displayid>51519</displayid>
<displayslot>8</displayslot>
<iconpath>inv_boots_leather01</iconpath>
<stats>
<armor>375</armor>
<agility>33</agility>
<stamina>61</stamina>
<attackpower>100</attackpower>
<hasterating>50</hasterating>
</stats>
<quality>Rare</quality>
<type>Leather</type>
<faction>Neutral</faction>
<bind>BoP</bind>
<socketcolor1>Red</socketcolor1>
<socketbonus>
<stamina>6</stamina>
</socketbonus>
<name>Gorloc Muddy Footwraps</name>
<id>43312</id>
<slot>Feet</slot>
</item>