<item>
<itemlevel>200</itemlevel>
<displayid>53286</displayid>
<displayslot>7</displayslot>
<iconpath>inv_pants_plate_21</iconpath>
<stats>
<armor>1961</armor>
<stamina>123</stamina>
<strength>68</strength>
<hitrating>45</hitrating>
<defenserating>81</defenserating>
</stats>
<quality>Epic</quality>
<type>Plate</type>
<faction>Neutral</faction>
<bind>BoP</bind>
<socketcolor1>Red</socketcolor1>
<socketbonus>
<stamina>6</stamina>
</socketbonus>
<name>Bolstered Legplates</name>
<id>43500</id>
<slot>Legs</slot>
</item>