<item>
<itemlevel>187</itemlevel>
<displayid>56183</displayid>
<displayslot>7</displayslot>
<iconpath>inv_pants_plate_23</iconpath>
<stats>
<armor>1831</armor>
<stamina>102</stamina>
<strength>30</strength>
<hitrating>46</hitrating>
<defenserating>69</defenserating>
</stats>
<quality>Rare</quality>
<type>Plate</type>
<faction>Neutral</faction>
<bind>BoP</bind>
<socketcolor1>Red</socketcolor1>
<socketbonus>
<strength>4</strength>
</socketbonus>
<name>Special Issue Legplates</name>
<id>44240</id>
<slot>Legs</slot>
</item>