<item>
<itemlevel>258</itemlevel>
<displayid>61825</displayid>
<displayslot>5</displayslot>
<iconpath>inv_chest_mail_07</iconpath>
<stats>
<armor>1448</armor>
<agility>86</agility>
<stamina>121</stamina>
<attackpower>274</attackpower>
<intellect>80</intellect>
<critrating>86</critrating>
<hasterating>80</hasterating>
</stats>
<quality>Epic</quality>
<type>Mail</type>
<faction>Alliance</faction>
<bind>BoP</bind>
<socketcolor1>Red</socketcolor1>
<socketcolor2>Blue</socketcolor2>
<socketcolor3>Yellow</socketcolor3>
<socketbonus>
<attackpower>16</attackpower>
</socketbonus>
<name>Breastplate of Cruel Intent</name>
<id>46965</id>
<slot>Chest</slot>
</item>