<item>
<itemlevel>245</itemlevel>
<displayid>61720</displayid>
<displayslot>20</displayslot>
<iconpath>inv_chest_leather_18b</iconpath>
<stats>
<armor>623</armor>
<stamina>103</stamina>
<intellect>103</intellect>
<spirit>90</spirit>
<spellpower>140</spellpower>
<hasterating>74</hasterating>
</stats>
<quality>Epic</quality>
<type>Leather</type>
<faction>Horde</faction>
<bind>BoP</bind>
<socketcolor1>Red</socketcolor1>
<socketcolor2>Blue</socketcolor2>
<socketbonus>
<spellpower>7</spellpower>
</socketbonus>
<name>Robes of the Shattered Fellowship</name>
<id>47292</id>
<slot>Chest</slot>
</item>