<item>
<itemlevel>258</itemlevel>
<displayid>0</displayid>
<displayslot>0</displayslot>
<iconpath>inv_shoulder_67</iconpath>
<stats>
<armor>1086</armor>
<stamina>86</stamina>
<intellect>86</intellect>
<spellpower>124</spellpower>
<hasterating>68</hasterating>
<mp5>38</mp5>
</stats>
<quality>Epic</quality>
<setname>Nobundo's Garb</setname>
<type>Mail</type>
<faction>Horde</faction>
<requiredclasses>Shaman</requiredclasses>
<bind>BoP</bind>
<socketcolor1>Blue</socketcolor1>
<socketbonus>
<spellpower>5</spellpower>
</socketbonus>
<name>Thrall's Spaulders of Triumph</name>
<id>48309</id>
<slot>Shoulders</slot>
</item>