<item>
<itemlevel>264</itemlevel>
<displayid>0</displayid>
<displayslot>0</displayslot>
<iconpath>inv_axe_113</iconpath>
<stats>
<stamina>185</stamina>
<strength>185</strength>
<armorpenetrationrating>92</armorpenetrationrating>
<critrating>92</critrating>
</stats>
<quality>Epic</quality>
<type>TwoHandAxe</type>
<faction>Neutral</faction>
<mindamage>872</mindamage>
<maxdamage>1309</maxdamage>
<speed>3.7</speed>
<requiredclasses>Warrior|Paladin|Death Knight</requiredclasses>
<unique>true</unique>
<bind>BoP</bind>
<socketcolor1>Red</socketcolor1>
<socketcolor2>Red</socketcolor2>
<socketbonus>
<strength>6</strength>
</socketbonus>
<name>Shadow's Edge</name>
<id>49888</id>
<slot>TwoHand</slot>
</item>