<item>
<itemlevel>251</itemlevel>
<displayid>0</displayid>
<displayslot>0</displayslot>
<iconpath>inv_helmet_156</iconpath>
<stats>
<armor>275</armor>
<stamina>109</stamina>
<intellect>109</intellect>
<spellpower>139</spellpower>
<critrating>96</critrating>
<hasterating>72</hasterating>
</stats>
<quality>Epic</quality>
<setname>Crimson Acolyte's Regalia</setname>
<type>Cloth</type>
<faction>Neutral</faction>
<requiredclasses>Priest</requiredclasses>
<bind>BoP</bind>
<socketcolor1>Meta</socketcolor1>
<socketcolor2>Blue</socketcolor2>
<socketbonus>
<spellpower>9</spellpower>
</socketbonus>
<name>Crimson Acolyte Cowl</name>
<id>50392</id>
<slot>Head</slot>
</item>