<item>
<itemlevel>264</itemlevel>
<displayid>0</displayid>
<displayslot>0</displayslot>
<iconpath>inv_kilt_cloth_02</iconpath>
<stats>
<armor>309</armor>
<stamina>123</stamina>
<intellect>123</intellect>
<spellpower>171</spellpower>
<critrating>108</critrating>
<hitrating>92</hitrating>
</stats>
<quality>Epic</quality>
<setname>Dark Coven's Regalia</setname>
<type>Cloth</type>
<faction>Neutral</faction>
<requiredclasses>Warlock</requiredclasses>
<bind>BoP</bind>
<socketcolor1>Blue</socketcolor1>
<socketcolor2>Yellow</socketcolor2>
<socketbonus>
<spellpower>7</spellpower>
</socketbonus>
<name>Sanctified Dark Coven Leggings</name>
<id>51207</id>
<slot>Legs</slot>
</item>